xhs_2_album/__init__.py
xhs_2_album-0.0.3.dist-info/LICENSE
xhs_2_album-0.0.3.dist-info/METADATA
xhs_2_album-0.0.3.dist-info/WHEEL
xhs_2_album-0.0.3.dist-info/top_level.txt
xhs_2_album-0.0.3.dist-info/RECORD
